{
  "type":"FeatureCollection",
  "name":"PARA Oberkirch",
  "description":"REST, PARA/AEROBATICS, 56137 - PARA Oberkirch",
  "extra":{
    "mapAttribute":"PARACHUTE"
  },
  "features":[ {
    "geometry":{
      "type":"Point",
      "coordinates":[ 1.0972222222222223, 44.97 ]
    },
    "type":"Feature",
    "properties":{
      "priority":15,
      "color":"#006699",
      "font":"MS Sans Serif",
      "remarks":"LEVEL/ll=000/ul=999/parachute/TEXT=DUMMY - PARA"
    }
  }, {
    "geometry":{
      "type":"Point",
      "coordinates":[ 8.078055555555556, 47.22666666666667 ]
    },
    "type":"Feature",
    "properties":{
      "priority":4,
      "color":"#505150",
      "font":"GraphicsGva",
      "size":200,
      "description":"LSPN",
      "info":{
        "elevation":1594,
        "additionalInfos":"",
        "name":"LSPN",
        "description":"TRIENGEN",
        "runways":[ {
          "surface":"CONC",
          "lda":"535/460/15",
          "runway":"15/33"
        } ],
        "frequencies":[ {
          "onSameLine":false,
          "name":"AD",
          "frequency":"124.530"
        } ]
      },
      "tooltipInfo":"LSPN/TRIENGEN\\AD: 124.530\\elevation 1594 ft\\RWY: 15/33 LDA: 535/460/15 - CONC",
      "symbol":"A_AERO_SYM3",
      "symbol_type":"AIRPORT",
      "runwaySymbol":"SYMB_ORIENT3"
    }
  }, {
    "geometry":{
      "type":"Point",
      "coordinates":[ 8.119444444444444, 47.15777777777778 ]
    },
    "type":"Feature",
    "properties":{
      "priority":18,
      "color":"#006699",
      "font":"GraphicsGva",
      "size":200,
      "description":"PJOBR",
      "symbol":"A_SYMBOL_SYM31",
      "symbol_type":"WAYPOINT",
      "info":{
        "additionalInfos":"",
        "name":"PJOBR",
        "coordinates":"47.09.28N  08.07.10E",
        "description":"PARA OBERKIRCH"
      },
      "tooltipInfo":"PARA OBERKIRCH"
    }
  } ]
}