{
  "type":"FeatureCollection",
  "name":"PARA Duebendorf",
  "description":"REST, PARA/AEROBATICS, 56140 - PARA Duebendorf",
  "extra":{
    "mapAttribute":"PARACHUTE"
  },
  "features":[ {
    "geometry":{
      "type":"Point",
      "coordinates":[ 1.0972222222222223, 44.97 ]
    },
    "type":"Feature",
    "properties":{
      "priority":15,
      "color":"#006699",
      "font":"MS Sans Serif",
      "remarks":"LEVEL/ll=000/ul=999/parachute/TEXT=DUMMY - PARA"
    }
  }, {
    "geometry":{
      "type":"Point",
      "coordinates":[ 8.648333333333333, 47.39833333333333 ]
    },
    "type":"Feature",
    "properties":{
      "priority":4,
      "color":"#505150",
      "font":"GraphicsGva",
      "size":200,
      "description":"LSMD",
      "info":{
        "elevation":1450,
        "additionalInfos":"ILS29: 111.150 Track 286",
        "name":"LSMD",
        "description":"DUEBENDORF",
        "runways":[ {
          "surface":"CONC",
          "lda":"2355/2300/40",
          "runway":"11/29"
        } ],
        "frequencies":[ {
          "onSameLine":false,
          "name":"RADAR",
          "frequency":"134.925"
        }, {
          "onSameLine":false,
          "name":"TWR",
          "frequency":"118.975"
        } ]
      },
      "tooltipInfo":"LSMD/DUEBENDORF\\ILS29: 111.150 Track 286\\RADAR: 134.925\\TWR: 118.975\\elevation 1450 ft\\RWY: 11/29 LDA: 2355/2300/40 - CONC",
      "symbol":"A_AERO_SYM4",
      "symbol_type":"AIRPORT",
      "runwaySymbol":"SYMB_ORIENT7"
    }
  }, {
    "geometry":{
      "type":"Point",
      "coordinates":[ 8.619722222222222, 47.38777777777778 ]
    },
    "type":"Feature",
    "properties":{
      "priority":18,
      "color":"#006699",
      "font":"GraphicsGva",
      "size":200,
      "description":"PJDUB",
      "symbol":"A_SYMBOL_SYM31",
      "symbol_type":"WAYPOINT",
      "info":{
        "additionalInfos":"",
        "name":"PJDUB",
        "coordinates":"47.23.16N  08.37.11E",
        "description":"PARA DUEBENDORF"
      },
      "tooltipInfo":"PARA DUEBENDORF"
    }
  } ]
}